pymerum/__init__.py
pymerum/__init__.pyi
pymerum/kanji.py
pymerum/kanji.pyi
pymerum/legacy.py
pymerum/legacy.pyi
pymerum/merum.py
pymerum/merum.pyi
pymerum/properties.py
pymerum/properties.pyi
pymerum/py.typed
pymerum/scripts.py
pymerum/scripts.pyi
pymerum/data/halfhor3.db
pymerum/data/itaijidict4.db
pymerum/data/kanwadict4.db
pymerum/data/kunreidict3.db
pymerum/data/kunreiharu3.db
pymerum/data/marburudict3.db
pymerum/data/marburuharu3.db
pymerum/data/passportdict3.db
pymerum/data/passportharu3.db
pymerum-0.0.2.dist-info/METADATA
pymerum-0.0.2.dist-info/WHEEL
pymerum-0.0.2.dist-info/top_level.txt
pymerum-0.0.2.dist-info/RECORD
